[
  {
    "url": "http://www.aberdeen-md.org/",
    "long": "-76.16",
    "name": "Aberdeen",
    "state": {
      "name": "Maryland",
      "abbreviation": "MD"
    },
    "lat": "39.5"
  },
  {
    "url": "http://www.ci.annapolis.md.us/",
    "long": "-76.49",
    "name": "Annapolis",
    "state": {
      "name": "Maryland",
      "abbreviation": "MD"
    },
    "lat": "38.97"
  },
  {
    "url": "http://www.baltimorecity.gov/",
    "long": "-76.61",
    "name": "Baltimore",
    "state": {
      "name": "Maryland",
      "abbreviation": "MD"
    },
    "lat": "39.29"
  },
  {
    "url": "http://www.barnesvillemd.org/",
    "long": "-77.37",
    "name": "Barnesville",
    "state": {
      "name": "Maryland",
      "abbreviation": "MD"
    },
    "lat": "39.22"
  },
  {
    "url": "http://www.belairmd.org/",
    "long": "-76.34",
    "name": "Bel Air",
    "state": {
      "name": "Maryland",
      "abbreviation": "MD"
    },
    "lat": "39.53"
  },
  {
    "url": "http://www.townofberlinmd.com/",
    "long": "-75.21",
    "name": "Berlin",
    "state": {
      "name": "Maryland",
      "abbreviation": "MD"
    },
    "lat": "38.32"
  },
  {
    "url": "http://www.berwyn-heights.com/",
    "long": "-76.91",
    "name": "Berwyn Heights",
    "state": {
      "name": "Maryland",
      "abbreviation": "MD"
    },
    "lat": "38.99"
  },
  {
    "url": "http://www.bladensburg.com/",
    "long": "-76.93",
    "name": "Bladensburg",
    "state": {
      "name": "Maryland",
      "abbreviation": "MD"
    },
    "lat": "38.93"
  },
  {
    "url": "http://www.boonsboro.org/",
    "long": "-77.65",
    "name": "Boonsboro",
    "state": {
      "name": "Maryland",
      "abbreviation": "MD"
    },
    "lat": "39.5"
  },
  {
    "url": "http://www.cityofbowie.org/",
    "long": "-76.77",
    "name": "Bowie",
    "state": {
      "name": "Maryland",
      "abbreviation": "MD"
    },
    "lat": "39"
  },
  {
    "url": "http://www.townofbrentwood-md.us/",
    "long": "-76.95",
    "name": "Brentwood",
    "state": {
      "name": "Maryland",
      "abbreviation": "MD"
    },
    "lat": "38.94"
  },
  {
    "url": "http://townofbrookevillemd.org/",
    "long": "-77.05",
    "name": "Brookeville",
    "state": {
      "name": "Maryland",
      "abbreviation": "MD"
    },
    "lat": "39.18"
  },
  {
    "url": "http://www.brunswickmd.gov/",
    "long": "-77.62",
    "name": "Brunswick",
    "state": {
      "name": "Maryland",
      "abbreviation": "MD"
    },
    "lat": "39.31"
  },
  {
    "url": "http://www.ci.cambridge.md.us/",
    "long": "-76.07",
    "name": "Cambridge",
    "state": {
      "name": "Maryland",
      "abbreviation": "MD"
    },
    "lat": "38.56"
  },
  {
    "url": "http://www.ceciltonmd.gov/",
    "long": "-75.86",
    "name": "Cecilton",
    "state": {
      "name": "Maryland",
      "abbreviation": "MD"
    },
    "lat": "39.4"
  },
  {
    "url": "http://www.townofcentreville.org/",
    "long": "-76.06",
    "name": "Centreville",
    "state": {
      "name": "Maryland",
      "abbreviation": "MD"
    },
    "lat": "39.04"
  },
  {
    "url": "http://www.charlestownmd.org/",
    "long": "-75.97",
    "name": "Charlestown",
    "state": {
      "name": "Maryland",
      "abbreviation": "MD"
    },
    "lat": "39.57"
  },
  {
    "url": "http://chesapeake-beach.md.us/",
    "long": "-76.53",
    "name": "Chesapeake Beach",
    "state": {
      "name": "Maryland",
      "abbreviation": "MD"
    },
    "lat": "38.68"
  },
  {
    "url": "http://www.chesapeakecity.com/",
    "long": "-75.8",
    "name": "Chesapeake City",
    "state": {
      "name": "Maryland",
      "abbreviation": "MD"
    },
    "lat": "39.53"
  },
  {
    "url": "http://chestertown.com/gov/",
    "long": "-76.06",
    "name": "Chestertown",
    "state": {
      "name": "Maryland",
      "abbreviation": "MD"
    },
    "lat": "39.2"
  },
  {
    "url": "http://www.cheverly.com/",
    "long": "-76.91",
    "name": "Cheverly",
    "state": {
      "name": "Maryland",
      "abbreviation": "MD"
    },
    "lat": "38.92"
  },
  {
    "url": "http://www.chevychasesection5.org/",
    "long": "-77.07",
    "name": "Chevy Chase Section Five",
    "state": {
      "name": "Maryland",
      "abbreviation": "MD"
    },
    "lat": "38.98"
  },
  {
    "url": "http://www.chevychasesection3.org/",
    "long": "-77.07",
    "name": "Chevy Chase Section Three",
    "state": {
      "name": "Maryland",
      "abbreviation": "MD"
    },
    "lat": "38.97"
  },
  {
    "url": "http://www.chevychaseview.org/",
    "long": "-77.08",
    "name": "Chevy Chase View",
    "state": {
      "name": "Maryland",
      "abbreviation": "MD"
    },
    "lat": "39.01"
  },
  {
    "url": "http://www.ccvillage.org/",
    "long": "-77.07",
    "name": "Chevy Chase Village",
    "state": {
      "name": "Maryland",
      "abbreviation": "MD"
    },
    "lat": "38.96"
  },
  {
    "url": "http://www.collegeparkmd.gov/",
    "long": "-76.93",
    "name": "College Park",
    "state": {
      "name": "Maryland",
      "abbreviation": "MD"
    },
    "lat": "38.98"
  },
  {
    "url": "http://www.cityofcrisfield-md.gov/",
    "long": "-75.85",
    "name": "Crisfield",
    "state": {
      "name": "Maryland",
      "abbreviation": "MD"
    },
    "lat": "37.98"
  },
  {
    "url": "http://www.ci.cumberland.md.us/",
    "long": "-78.76",
    "name": "Cumberland",
    "state": {
      "name": "Maryland",
      "abbreviation": "MD"
    },
    "lat": "39.65"
  },
  {
    "url": "http://www.dentonmaryland.com/",
    "long": "-75.82",
    "name": "Denton",
    "state": {
      "name": "Maryland",
      "abbreviation": "MD"
    },
    "lat": "38.88"
  },
  {
    "url": "http://www.districtheights.org/",
    "long": "-76.88",
    "name": "District Heights",
    "state": {
      "name": "Maryland",
      "abbreviation": "MD"
    },
    "lat": "38.85"
  },
  {
    "url": "http://www.town-eastonmd.com/",
    "long": "-76.07",
    "name": "Easton",
    "state": {
      "name": "Maryland",
      "abbreviation": "MD"
    },
    "lat": "38.77"
  },
  {
    "url": "http://www.townofelkton.org/",
    "long": "-75.83",
    "name": "Elkton",
    "state": {
      "name": "Maryland",
      "abbreviation": "MD"
    },
    "lat": "39.6"
  },
  {
    "url": "http://www.emmitsburg.net/towngov/",
    "long": "-77.32",
    "name": "Emmitsburg",
    "state": {
      "name": "Maryland",
      "abbreviation": "MD"
    },
    "lat": "39.7"
  },
  {
    "url": "http://www.federalsburg.org/",
    "long": "-75.77",
    "name": "Federalsburg",
    "state": {
      "name": "Maryland",
      "abbreviation": "MD"
    },
    "lat": "38.69"
  },
  {
    "url": "http://www.cityoffrederick.com/",
    "long": "-77.41",
    "name": "Frederick",
    "state": {
      "name": "Maryland",
      "abbreviation": "MD"
    },
    "lat": "39.41"
  },
  {
    "url": "http://www.ci.frostburg.md.us/",
    "long": "-78.92",
    "name": "Frostburg",
    "state": {
      "name": "Maryland",
      "abbreviation": "MD"
    },
    "lat": "39.65"
  },
  {
    "url": "http://www.cityoffruitland.com/",
    "long": "-75.62",
    "name": "Fruitland",
    "state": {
      "name": "Maryland",
      "abbreviation": "MD"
    },
    "lat": "38.32"
  },
  {
    "url": "http://www.gaithersburgmd.gov/",
    "long": "-77.2",
    "name": "Gaithersburg",
    "state": {
      "name": "Maryland",
      "abbreviation": "MD"
    },
    "lat": "39.14"
  },
  {
    "url": "http://www.garrettpark-md.gov",
    "long": "-77.09",
    "name": "Garrett Park",
    "state": {
      "name": "Maryland",
      "abbreviation": "MD"
    },
    "lat": "39.03"
  },
  {
    "url": "http://www.glenecho.org/",
    "long": "-77.14",
    "name": "Glen Echo",
    "state": {
      "name": "Maryland",
      "abbreviation": "MD"
    },
    "lat": "38.96"
  },
  {
    "url": "http://www.cityofglenarden.org/",
    "long": "-76.86",
    "name": "Glenarden",
    "state": {
      "name": "Maryland",
      "abbreviation": "MD"
    },
    "lat": "38.92"
  },
  {
    "url": "http://www.greenbeltmd.gov/",
    "long": "-76.87",
    "name": "Greenbelt",
    "state": {
      "name": "Maryland",
      "abbreviation": "MD"
    },
    "lat": "39"
  },
  {
    "url": "http://www.greensboromd.com/",
    "long": "-75.8",
    "name": "Greensboro",
    "state": {
      "name": "Maryland",
      "abbreviation": "MD"
    },
    "lat": "38.97"
  },
  {
    "url": "http://www.hagerstownmd.org/",
    "long": "-77.71",
    "name": "Hagerstown",
    "state": {
      "name": "Maryland",
      "abbreviation": "MD"
    },
    "lat": "39.64"
  },
  {
    "url": "http://www.townofhampstead.us/",
    "long": "-76.84",
    "name": "Hampstead",
    "state": {
      "name": "Maryland",
      "abbreviation": "MD"
    },
    "lat": "39.6"
  },
  {
    "url": "http://www.havredegracemd.com/",
    "long": "-76.09",
    "name": "Havre de Grace",
    "state": {
      "name": "Maryland",
      "abbreviation": "MD"
    },
    "lat": "39.54"
  },
  {
    "url": "http://www.hurlock-md.gov/",
    "long": "-75.85",
    "name": "Hurlock",
    "state": {
      "name": "Maryland",
      "abbreviation": "MD"
    },
    "lat": "38.62"
  },
  {
    "url": "http://www.hyattsville.org/",
    "long": "-76.94",
    "name": "Hyattsville",
    "state": {
      "name": "Maryland",
      "abbreviation": "MD"
    },
    "lat": "38.95"
  },
  {
    "url": "http://www.townofindianheadmd.org/",
    "long": "-77.16",
    "name": "Indian Head",
    "state": {
      "name": "Maryland",
      "abbreviation": "MD"
    },
    "lat": "38.6"
  },
  {
    "url": "http://tok.md.gov/",
    "long": "-77.07",
    "name": "Kensington",
    "state": {
      "name": "Maryland",
      "abbreviation": "MD"
    },
    "lat": "39.02"
  },
  {
    "url": "http://myweb.cebridge.net/townofkitzmiller/",
    "long": "-79.18",
    "name": "Kitzmiller",
    "state": {
      "name": "Maryland",
      "abbreviation": "MD"
    },
    "lat": "39.38"
  },
  {
    "url": "http://www.townoflaplata.org/",
    "long": "-76.97",
    "name": "La Plata",
    "state": {
      "name": "Maryland",
      "abbreviation": "MD"
    },
    "lat": "38.52"
  },
  {
    "url": "http://www.lhills.sailorsite.net/",
    "long": "-76.89",
    "name": "Landover Hills",
    "state": {
      "name": "Maryland",
      "abbreviation": "MD"
    },
    "lat": "38.94"
  },
  {
    "url": "http://www.laurel.md.us/",
    "long": "-76.84",
    "name": "Laurel",
    "state": {
      "name": "Maryland",
      "abbreviation": "MD"
    },
    "lat": "39.09"
  },
  {
    "url": "http://www.laytonsville.md.us/",
    "long": "-77.14",
    "name": "Laytonsville",
    "state": {
      "name": "Maryland",
      "abbreviation": "MD"
    },
    "lat": "39.21"
  },
  {
    "url": "http://leonardtown.somd.com/",
    "long": "-76.63",
    "name": "Leonardtown",
    "state": {
      "name": "Maryland",
      "abbreviation": "MD"
    },
    "lat": "38.29"
  },
  {
    "url": "http://manchestermd.org/",
    "long": "-76.88",
    "name": "Manchester",
    "state": {
      "name": "Maryland",
      "abbreviation": "MD"
    },
    "lat": "39.66"
  },
  {
    "url": "http://www.martinsadditions.org/",
    "long": "-77.06",
    "name": "Martins Additions",
    "state": {
      "name": "Maryland",
      "abbreviation": "MD"
    },
    "lat": "38.97"
  },
  {
    "url": "http://www.middletown.md.us/",
    "long": "-77.54",
    "name": "Middletown",
    "state": {
      "name": "Maryland",
      "abbreviation": "MD"
    },
    "lat": "39.44"
  },
  {
    "url": "http://www.town.morningside.md.us/",
    "long": "-76.89",
    "name": "Morningside",
    "state": {
      "name": "Maryland",
      "abbreviation": "MD"
    },
    "lat": "38.83"
  },
  {
    "url": "http://www.mountairymd.org/",
    "long": "-77.15",
    "name": "Mount Airy",
    "state": {
      "name": "Maryland",
      "abbreviation": "MD"
    },
    "lat": "39.37"
  },
  {
    "url": "http://www.mountrainiermd.org/",
    "long": "-76.96",
    "name": "Mount Rainier",
    "state": {
      "name": "Maryland",
      "abbreviation": "MD"
    },
    "lat": "38.94"
  },
  {
    "url": "http://www.mtnlakepark.com/",
    "long": "-79.38",
    "name": "Mountain Lake Park",
    "state": {
      "name": "Maryland",
      "abbreviation": "MD"
    },
    "lat": "39.39"
  },
  {
    "url": "http://www.myersvillemd.govoffice2.com/",
    "long": "-77.56",
    "name": "Myersville",
    "state": {
      "name": "Maryland",
      "abbreviation": "MD"
    },
    "lat": "39.5"
  },
  {
    "url": "http://www.new-carrollton.md.us/",
    "long": "-76.87",
    "name": "New Carrollton",
    "state": {
      "name": "Maryland",
      "abbreviation": "MD"
    },
    "lat": "38.96"
  },
  {
    "url": "http://www.townofnewmarket.org/",
    "long": "-77.26",
    "name": "New Market",
    "state": {
      "name": "Maryland",
      "abbreviation": "MD"
    },
    "lat": "39.38"
  },
  {
    "url": "http://www.newwindsormd.org/",
    "long": "-77.1",
    "name": "New Windsor",
    "state": {
      "name": "Maryland",
      "abbreviation": "MD"
    },
    "lat": "39.54"
  },
  {
    "url": "http://www.ci.north-beach.md.us/",
    "long": "-76.53",
    "name": "North Beach",
    "state": {
      "name": "Maryland",
      "abbreviation": "MD"
    },
    "lat": "38.7"
  },
  {
    "url": "http://www.northbrentwood.com/",
    "long": "-76.95",
    "name": "North Brentwood",
    "state": {
      "name": "Maryland",
      "abbreviation": "MD"
    },
    "lat": "38.94"
  },
  {
    "url": "http://www.northchevychase.org/",
    "long": "-77.07",
    "name": "North Chevy Chase",
    "state": {
      "name": "Maryland",
      "abbreviation": "MD"
    },
    "lat": "39"
  },
  {
    "url": "http://www.northeastmd.org/",
    "long": "-75.94",
    "name": "North East",
    "state": {
      "name": "Maryland",
      "abbreviation": "MD"
    },
    "lat": "39.6"
  },
  {
    "url": "http://www.oceancitymd.gov/",
    "long": "-75.08",
    "name": "Ocean City",
    "state": {
      "name": "Maryland",
      "abbreviation": "MD"
    },
    "lat": "38.33"
  },
  {
    "url": "http://www.oxfordmd.net/",
    "long": "-76.17",
    "name": "Oxford",
    "state": {
      "name": "Maryland",
      "abbreviation": "MD"
    },
    "lat": "38.68"
  },
  {
    "url": "http://www.perryvillemd.org/",
    "long": "-76.07",
    "name": "Perryville",
    "state": {
      "name": "Maryland",
      "abbreviation": "MD"
    },
    "lat": "39.56"
  },
  {
    "url": "http://www.cityofpocomoke.com/",
    "long": "-75.56",
    "name": "Pocomoke City",
    "state": {
      "name": "Maryland",
      "abbreviation": "MD"
    },
    "lat": "38.07"
  },
  {
    "url": "http://www.ci.poolesville.md.us/",
    "long": "-77.41",
    "name": "Poolesville",
    "state": {
      "name": "Maryland",
      "abbreviation": "MD"
    },
    "lat": "39.14"
  },
  {
    "url": "http://www.portdeposit.org/",
    "long": "-76.11",
    "name": "Port Deposit",
    "state": {
      "name": "Maryland",
      "abbreviation": "MD"
    },
    "lat": "39.6"
  },
  {
    "url": "http://www.queenstown-md.com/",
    "long": "-76.15",
    "name": "Queenstown",
    "state": {
      "name": "Maryland",
      "abbreviation": "MD"
    },
    "lat": "38.99"
  },
  {
    "url": "http://www.ridgelymd.org/",
    "long": "-75.88",
    "name": "Ridgely",
    "state": {
      "name": "Maryland",
      "abbreviation": "MD"
    },
    "lat": "38.94"
  },
  {
    "url": "http://www.ci.riverdale-park.md.us/",
    "long": "-76.93",
    "name": "Riverdale Park",
    "state": {
      "name": "Maryland",
      "abbreviation": "MD"
    },
    "lat": "38.96"
  },
  {
    "url": "http://www.rockhallmd.com/gov/",
    "long": "-76.23",
    "name": "Rock Hall",
    "state": {
      "name": "Maryland",
      "abbreviation": "MD"
    },
    "lat": "39.13"
  },
  {
    "url": "http://www.rockvillemd.gov/",
    "long": "-77.15",
    "name": "Rockville",
    "state": {
      "name": "Maryland",
      "abbreviation": "MD"
    },
    "lat": "39.08"
  },
  {
    "url": "http://www.ci.salisbury.md.us/",
    "long": "-75.59",
    "name": "Salisbury",
    "state": {
      "name": "Maryland",
      "abbreviation": "MD"
    },
    "lat": "38.36"
  },
  {
    "url": "http://www.seatpleasantmd.gov/",
    "long": "-76.9",
    "name": "Seat Pleasant",
    "state": {
      "name": "Maryland",
      "abbreviation": "MD"
    },
    "lat": "38.89"
  },
  {
    "url": "http://www.wc-link.org/smithsburg/",
    "long": "-77.57",
    "name": "Smithsburg",
    "state": {
      "name": "Maryland",
      "abbreviation": "MD"
    },
    "lat": "39.65"
  },
  {
    "url": "http://www.snowhillmd.com/",
    "long": "-75.39",
    "name": "Snow Hill",
    "state": {
      "name": "Maryland",
      "abbreviation": "MD"
    },
    "lat": "38.17"
  },
  {
    "url": "http://townofsomerset.com/",
    "long": "-77.09",
    "name": "Somerset",
    "state": {
      "name": "Maryland",
      "abbreviation": "MD"
    },
    "lat": "38.96"
  },
  {
    "url": "http://www.sudlersville.org/",
    "long": "-75.85",
    "name": "Sudlersville",
    "state": {
      "name": "Maryland",
      "abbreviation": "MD"
    },
    "lat": "39.18"
  },
  {
    "url": "http://www.sykesville.net/",
    "long": "-76.96",
    "name": "Sykesville",
    "state": {
      "name": "Maryland",
      "abbreviation": "MD"
    },
    "lat": "39.37"
  },
  {
    "url": "http://www.takomaparkmd.gov/",
    "long": "-77",
    "name": "Takoma Park",
    "state": {
      "name": "Maryland",
      "abbreviation": "MD"
    },
    "lat": "38.97"
  },
  {
    "url": "http://www.taneytown.org/",
    "long": "-77.17",
    "name": "Taneytown",
    "state": {
      "name": "Maryland",
      "abbreviation": "MD"
    },
    "lat": "39.65"
  },
  {
    "url": "http://www.thurmont.com/",
    "long": "-77.41",
    "name": "Thurmont",
    "state": {
      "name": "Maryland",
      "abbreviation": "MD"
    },
    "lat": "39.62"
  },
  {
    "url": "http://trappemd.net/",
    "long": "-76.05",
    "name": "Trappe",
    "state": {
      "name": "Maryland",
      "abbreviation": "MD"
    },
    "lat": "38.65"
  },
  {
    "url": "http://www.carr.org/~unionbr/",
    "long": "-77.17",
    "name": "Union Bridge",
    "state": {
      "name": "Maryland",
      "abbreviation": "MD"
    },
    "lat": "39.56"
  },
  {
    "url": "http://www.upmd.org/",
    "long": "-76.94",
    "name": "University Park",
    "state": {
      "name": "Maryland",
      "abbreviation": "MD"
    },
    "lat": "38.97"
  },
  {
    "url": "http://www.washingtongrovemd.org/",
    "long": "-77.17",
    "name": "Washington Grove",
    "state": {
      "name": "Maryland",
      "abbreviation": "MD"
    },
    "lat": "39.13"
  },
  {
    "url": "http://www.westgov.com/",
    "long": "-76.99",
    "name": "Westminster",
    "state": {
      "name": "Maryland",
      "abbreviation": "MD"
    },
    "lat": "39.57"
  },
  {
    "url": "http://www.mountairymd.org/",
    "long": "-77.15",
    "name": "Mount Airy",
    "state": {
      "name": "Maryland",
      "abbreviation": "MD"
    },
    "lat": "39.37"
  },
  {
    "url": "http://www.takomaparkmd.gov/",
    "long": "-77",
    "name": "Takoma Park",
    "state": {
      "name": "Maryland",
      "abbreviation": "MD"
    },
    "lat": "38.97"
  }
]